gcont/__init__.py
gcont/main.py
gcont-0.1.5.dist-info/LICENCE
gcont-0.1.5.dist-info/METADATA
gcont-0.1.5.dist-info/WHEEL
gcont-0.1.5.dist-info/entry_points.txt
gcont-0.1.5.dist-info/top_level.txt
gcont-0.1.5.dist-info/RECORD
