Metadata-Version: 2.1
Name: gcont
Version: 0.1.5
Summary: A tool for gathering and documenting project files.
Home-page: https://github.com/ayoubachak/gcont
Author: Ayoub Achak
Author-email: ayoub.achak01@gmail.com
Classifier: Programming Language :: Python :: 3
Classifier: License :: OSI Approved :: MIT License
Classifier: Operating System :: OS Independent
Requires-Python: >=3.6
License-File: LICENCE
Requires-Dist: pyyaml
